README.rst
setup.py
PyMUSE/__init__.py
PyMUSE/musecube.py
PyMUSE/musecube_old.py
PyMUSE/roipoly.py
PyMUSE/utils.py
PyMUSE.egg-info/PKG-INFO
PyMUSE.egg-info/SOURCES.txt
PyMUSE.egg-info/dependency_links.txt
PyMUSE.egg-info/requires.txt
PyMUSE.egg-info/top_level.txt