Metadata-Version: 1.0
Name: PyMUSE
Version: 0.4.5
Summary: Python software for handling VLT/MUSE data.
Home-page: https://github.com/ismaelpessa/PyMUSE
Author: I. Pessa
Author-email: ismael.pessa@gmail.com
License: MIT
Platform: UNKNOWN
